Metadata-Version: 1.0
Name: sunniest
Version: 0.1
Summary: The Sunniest day in the world
Home-page: https://github.com/pypa//sunniest
Author: Tejashree Jagtap
Author-email: tjagtap@apple.com
License: Apple
Platform: UNKNOWN
